.coveragerc
.editorconfig
.gitignore
.travis.yml
LICENSE
README.md
pyproject.toml
requirements.txt
requirements_dev.txt
setup.cfg
setup.py
.github/workflows/python-publish.yml
democritus_hypothesis/__init__.py
democritus_hypothesis/hypothesis_wrapper.py
democritus_hypothesis.egg-info/PKG-INFO
democritus_hypothesis.egg-info/SOURCES.txt
democritus_hypothesis.egg-info/dependency_links.txt
democritus_hypothesis.egg-info/requires.txt
democritus_hypothesis.egg-info/top_level.txt
democritus_hypothesis.egg-info/zip-safe
tests/__init__.py
tests/test_hypothesis_wrapper.py